ig/__init__.py
ig/alerts_pb2.py
ig/get_business_competitors_media.py
ig/get_business_insights.py
ig/get_business_media.py
ig/get_business_media_insights.py
ig/get_hashtag_media.py
ig/get_user_media.py
ig/instagram_utils.py
ig/validate_tokens.py
ig/conf/__init__.py
ig/conf/get_business_competitors_media.yaml
ig/conf/get_business_competitors_media_ondemand.yaml
ig/conf/get_business_insights.yaml
ig/conf/get_business_insights_ondemand.yaml
ig/conf/get_business_media.yaml
ig/conf/get_business_media_insights.yaml
ig/conf/get_business_media_insights_ondemand.yaml
ig/conf/get_business_media_ondemand.yaml
ig/conf/get_hashtag_media.yaml
ig/conf/get_hashtag_media_ondemand.yaml
ig/conf/get_user_media.yaml
ig/conf/validate_tokens.yaml
ig/conf/validate_tokens_fb.yaml
sinnia_ig_fetcher-0.2.15.dist-info/METADATA
sinnia_ig_fetcher-0.2.15.dist-info/WHEEL
sinnia_ig_fetcher-0.2.15.dist-info/top_level.txt
sinnia_ig_fetcher-0.2.15.dist-info/RECORD
