Metadata-Version: 2.1
Name: sinnia-ig-fetcher
Version: 0.2.15
Summary: Sinnia IG Fetching Tools
Home-page: https://github.com/sinnia/scripts/tree/develop/instagram
Author: Sinnia
Author-email: sonia.segura@sinnia.com
License: UNKNOWN
Platform: UNKNOWN
Requires-Dist: python-instagram
Requires-Dist: instagram
Requires-Dist: pymysql
Requires-Dist: pyyaml
Requires-Dist: requests
Requires-Dist: sinnia-shared
